examples/example_basic.py
examples/example_batch.py
examples/example_logo.py
musicard/__init__.py
musicard/card.py
musicard/cli.py
musicard/assets/PlusJakartaSans-Bold.ttf
musicard/assets/PlusJakartaSans-ExtraBold.ttf
musicard/assets/PlusJakartaSans-ExtraLight.ttf
musicard/assets/PlusJakartaSans-Light.ttf
musicard/assets/PlusJakartaSans-Medium.ttf
musicard/assets/PlusJakartaSans-Regular.ttf
musicard/assets/PlusJakartaSans-SemiBold.ttf
musicard/assets/output-classic.png
musicard/assets/output-classicpro.png
musicard/assets/output-dynamic.png
musicard/assets/output-mini.png
musicard/assets/output-upcoming.png
musicard/core/__init__.py
musicard/core/musicard.py
musicard/fonts/PlusJakartaSans-Bold.ttf
musicard/fonts/PlusJakartaSans-ExtraBold.ttf
musicard/fonts/PlusJakartaSans-ExtraLight.ttf
musicard/fonts/PlusJakartaSans-Light.ttf
musicard/fonts/PlusJakartaSans-Medium.ttf
musicard/fonts/PlusJakartaSans-Regular.ttf
musicard/fonts/PlusJakartaSans-SemiBold.ttf
musicard/templates/__init__.py
musicard/templates/base_theme.py
musicard/templates/classic.py
musicard/templates/classic_pro.py
musicard/templates/dynamic.py
musicard/templates/mini.py
musicard/templates/upcoming.py
musicard/utils/__init__.py
musicard/utils/cache.py
musicard/utils/fonts.py
musicard/utils/images.py
musicard/utils/svg.py
musicard/utils/text.py
musicard_py-2.2.0.dist-info/licenses/LICENSE
tests/test_basic.py
tests/test_musicard.py
musicard_py-2.2.0.dist-info/METADATA
musicard_py-2.2.0.dist-info/WHEEL
musicard_py-2.2.0.dist-info/entry_points.txt
musicard_py-2.2.0.dist-info/top_level.txt
musicard_py-2.2.0.dist-info/RECORD
