Metadata-Version: 2.4
Name: musicard-py
Version: 2.2.0
Summary: 🎵 Generate stunning music card images in Python with multiple themes, SVG export, and advanced customization. Inspired by unburn/musicard.
Author-email: Ramkrishna <ramkrishna@code-xon.fun>
Maintainer-email: Ramkrishna <ramkrishna@code-xon.fun>
License: MIT
Project-URL: Homepage, https://github.com/code-xon/musicard-py
Project-URL: Repository, https://github.com/code-xon/musicard-py
Project-URL: Documentation, https://github.com/code-xon/musicard-py#readme
Project-URL: Issues, https://github.com/code-xon/musicard-py/issues
Project-URL: Source, https://github.com/code-xon/musicard-py
Project-URL: Tracker, https://github.com/code-xon/musicard-py/issues
Keywords: music,card,image,generator,pillow,discord,bot,canvas,svg,themes,customization
Classifier: Development Status :: 5 - Production/Stable
Classifier: Intended Audience :: Developers
Classifier: License :: OSI Approved :: MIT License
Classifier: Programming Language :: Python :: 3
Classifier: Programming Language :: Python :: 3.8
Classifier: Programming Language :: Python :: 3.9
Classifier: Programming Language :: Python :: 3.10
Classifier: Programming Language :: Python :: 3.11
Classifier: Programming Language :: Python :: 3.12
Classifier: Programming Language :: Python :: 3.13
Classifier: Operating System :: OS Independent
Classifier: Topic :: Multimedia :: Graphics
Classifier: Topic :: Multimedia :: Graphics :: Graphics Conversion
Classifier: Topic :: Software Development :: Libraries :: Python Modules
Classifier: Topic :: Internet :: WWW/HTTP :: Dynamic Content
Requires-Python: >=3.8
License-File: LICENSE
Requires-Dist: Pillow>=10.0.0
Requires-Dist: requests>=2.25.0
Requires-Dist: cairosvg>=2.7.0
Requires-Dist: diskcache>=5.6.0
Dynamic: license-file
